[{"ProcedureJustification":{"id":1,"created_at":"2019-07-29 22:01:49","updated_at":"2019-07-29 22:30:41","justification":"Cierre del Establecimiento","procedure_id":5},"attach":[]},{"ProcedureJustification":{"id":2,"created_at":"2019-07-29 22:01:59","updated_at":"2019-07-29 22:30:51","justification":"Cambio de Propietario","procedure_id":5},"attach":[]},{"ProcedureJustification":{"id":3,"created_at":"2019-07-29 22:02:15","updated_at":"2019-07-29 22:31:00","justification":"Proceso de Liquidación","procedure_id":5},"attach":[]},{"ProcedureJustification":{"id":4,"created_at":"2019-07-29 22:02:34","updated_at":"2019-07-29 22:31:10","justification":"Ninguna","procedure_id":2},"attach":[]},{"ProcedureJustification":{"id":5,"created_at":"2019-07-29 22:02:40","updated_at":"2019-07-29 22:31:16","justification":"Ninguna","procedure_id":3},"attach":[]},{"ProcedureJustification":{"id":6,"created_at":"2019-07-29 22:02:47","updated_at":"2019-07-29 22:31:21","justification":"Ninguna","procedure_id":4},"attach":[]},{"ProcedureJustification":{"id":7,"created_at":"2019-07-29 22:02:54","updated_at":"2019-07-29 22:31:26","justification":"Ninguna","procedure_id":1},"attach":[]},{"ProcedureJustification":{"id":8,"created_at":"2019-08-06 15:08:52","updated_at":"2019-08-06 15:08:52","justification":"Recategorización","procedure_id":3},"attach":[]},{"ProcedureJustification":{"id":9,"created_at":"2019-08-06 15:14:04","updated_at":"2019-08-06 15:14:04","justification":"Reclasificación","procedure_id":2},"attach":[]},{"ProcedureJustification":{"id":10,"created_at":"2019-08-06 16:24:47","updated_at":"2019-08-06 16:24:47","justification":"Proceso de Liquidación","procedure_id":5},"attach":[]},{"ProcedureJustification":{"id":11,"created_at":"2019-08-08 14:35:38","updated_at":"2019-08-08 14:35:38","justification":"Reclasificación","procedure_id":2},"attach":[]},{"ProcedureJustification":{"id":12,"created_at":"2019-08-08 20:54:23","updated_at":"2019-08-08 20:54:23","justification":"Recategorización","procedure_id":3},"attach":[]},{"ProcedureJustification":{"id":13,"created_at":"2019-08-08 20:54:30","updated_at":"2019-08-08 20:54:30","justification":"Recategorización","procedure_id":3},"attach":[]},{"ProcedureJustification":{"id":14,"created_at":"2019-08-13 16:34:25","updated_at":"2019-08-13 16:34:25","justification":"Reclasificación","procedure_id":2},"attach":[]},{"ProcedureJustification":{"id":15,"created_at":"2019-08-13 16:34:27","updated_at":"2019-08-13 16:34:27","justification":"Reclasificación","procedure_id":2},"attach":[]},{"ProcedureJustification":{"id":16,"created_at":"2019-08-14 16:25:42","updated_at":"2019-08-14 16:25:42","justification":"Actualización","procedure_id":4},"attach":[]},{"ProcedureJustification":{"id":17,"created_at":"2019-08-14 17:12:06","updated_at":"2019-08-14 17:12:06","justification":"Recategorización","procedure_id":3},"attach":[]},{"ProcedureJustification":{"id":18,"created_at":"2019-08-15 17:55:44","updated_at":"2019-08-15 17:55:44","justification":"Actualización","procedure_id":4},"attach":[]},{"ProcedureJustification":{"id":19,"created_at":"2019-08-16 16:57:45","updated_at":"2019-08-16 16:57:45","justification":"Cierre del Establecimiento","procedure_id":5},"attach":[]},{"ProcedureJustification":{"id":20,"created_at":"2019-08-16 16:57:54","updated_at":"2019-08-16 16:57:54","justification":"Cierre del Establecimiento","procedure_id":5},"attach":[]},{"ProcedureJustification":{"id":21,"created_at":"2019-08-16 16:57:56","updated_at":"2019-08-16 16:57:56","justification":"Cierre del Establecimiento","procedure_id":5},"attach":[]},{"ProcedureJustification":{"id":22,"created_at":"2019-08-16 16:57:58","updated_at":"2019-08-16 16:57:58","justification":"Cierre del Establecimiento","procedure_id":5},"attach":[]},{"ProcedureJustification":{"id":23,"created_at":"2019-08-16 16:58:01","updated_at":"2019-08-16 16:58:01","justification":"Cierre del Establecimiento","procedure_id":5},"attach":[]},{"ProcedureJustification":{"id":24,"created_at":"2019-08-16 16:58:03","updated_at":"2019-08-16 16:58:03","justification":"Cierre del Establecimiento","procedure_id":5},"attach":[]},{"ProcedureJustification":{"id":25,"created_at":"2019-08-16 16:58:05","updated_at":"2019-08-16 16:58:05","justification":"Cierre del Establecimiento","procedure_id":5},"attach":[]},{"ProcedureJustification":{"id":26,"created_at":"2019-08-16 16:58:08","updated_at":"2019-08-16 16:58:08","justification":"Cierre del Establecimiento","procedure_id":5},"attach":[]},{"ProcedureJustification":{"id":27,"created_at":"2019-08-16 16:58:11","updated_at":"2019-08-16 16:58:11","justification":"Cierre del Establecimiento","procedure_id":5},"attach":[]},{"ProcedureJustification":{"id":28,"created_at":"2019-08-16 16:58:13","updated_at":"2019-08-16 16:58:13","justification":"Cierre del Establecimiento","procedure_id":5},"attach":[]},{"ProcedureJustification":{"id":29,"created_at":"2019-08-16 17:28:58","updated_at":"2019-08-16 17:28:58","justification":"Reclasificación","procedure_id":2},"attach":[]},{"ProcedureJustification":{"id":30,"created_at":"2019-08-16 19:41:05","updated_at":"2019-08-16 19:41:05","justification":"Recategorización","procedure_id":3},"attach":[]}]